py_smite/HiSpeed.py
py_smite/RED.py
py_smite/RED250mobile.py
py_smite/REDm.py
py_smite/REDn_Professional.py
py_smite/REDn_Scientific.py
py_smite/SMITE.py
py_smite/SMITE_Dummy.py
py_smite/SMITE_Dummy_raw.py
py_smite/SMITE_ET.py
py_smite/SMITE_raw.py
py_smite/__init__.py
py_smite/calibration_graphics.py
py_smite/helpers.py
py_smite/iViewXAPI.py
py_smite/iViewXAPIReturnCodes.py
py_smite/version.py
py_smite-1.1.dist-info/licenses/LICENSE.md
py_smite-1.1.dist-info/METADATA
py_smite-1.1.dist-info/WHEEL
py_smite-1.1.dist-info/top_level.txt
py_smite-1.1.dist-info/RECORD
