Metadata-Version: 2.4
Name: py_smite
Version: 1.1
Summary: SMITE is a toolbox for using eye trackers from SMI with Python, specifically offering integration with PsychoPy.
Home-page: https://github.com/marcus-nystrom/SMITE
Author: Marcus Nystrom
Author-email: marcus.nystrom@humlab.lu.se
License: Creative Commons Attribution 4.0 (CC BY 4.0)
Project-URL: Source Code, https://github.com/marcus-nystrom/SMITE
Classifier: Development Status :: 5 - Production/Stable
Classifier: Intended Audience :: Science/Research
Classifier: Topic :: Scientific/Engineering
Classifier: Topic :: Software Development :: Libraries
Classifier: Environment :: MacOS X
Classifier: Environment :: Win32 (MS Windows)
Classifier: Environment :: X11 Applications
Classifier: Operating System :: Microsoft :: Windows
Classifier: Operating System :: MacOS :: MacOS X
Classifier: Operating System :: POSIX :: Linux
Classifier: Programming Language :: Python :: 2
Requires-Python: >=2.7
License-File: LICENSE.md
Requires-Dist: numpy
Dynamic: author
Dynamic: author-email
Dynamic: classifier
Dynamic: description
Dynamic: description-content-type
Dynamic: home-page
Dynamic: license
Dynamic: license-file
Dynamic: project-url
Dynamic: requires-dist
Dynamic: requires-python
Dynamic: summary
